water/__init__.py
water/__main__.py
water/atexit_handler.py
water/display.py
water/monitor.py
water/queue.py
pywater-1.0.2.dist-info/LICENSE.txt
pywater-1.0.2.dist-info/METADATA
pywater-1.0.2.dist-info/WHEEL
pywater-1.0.2.dist-info/entry_points.txt
pywater-1.0.2.dist-info/top_level.txt
pywater-1.0.2.dist-info/RECORD
