Metadata-Version: 2.1
Name: pywater
Version: 1.0.2
Summary: water - watch execute repeat
Home-page: http://github.com/matutter/water
Author: Mathew Utter
Author-email: mcutter.svc@gmail.com
License: MIT
Keywords: python filesystem monitoring scripting task automation
Platform: UNKNOWN
Classifier: Development Status :: 4 - Beta
Classifier: Environment :: Console
Classifier: Intended Audience :: Developers
Classifier: License :: OSI Approved :: MIT License
Classifier: Natural Language :: English
Classifier: Operating System :: POSIX :: Linux
Classifier: Operating System :: MacOS :: MacOS X
Classifier: Operating System :: POSIX :: BSD
Classifier: Operating System :: Microsoft :: Windows :: Windows Vista
Classifier: Operating System :: Microsoft :: Windows :: Windows 7
Classifier: Operating System :: Microsoft :: Windows :: Windows 8
Classifier: Operating System :: Microsoft :: Windows :: Windows 8.1
Classifier: Operating System :: Microsoft :: Windows :: Windows 10
Classifier: Operating System :: OS Independent
Classifier: Programming Language :: Python
Classifier: Programming Language :: Python :: 3
Classifier: Programming Language :: Python :: 3 :: Only
Classifier: Programming Language :: Python :: 3.6
Classifier: Programming Language :: Python :: 3.7
Classifier: Programming Language :: Python :: 3.8
Classifier: Programming Language :: Python :: 3.9
Classifier: Programming Language :: Python :: 3.10
Classifier: Topic :: Software Development :: Build Tools
Classifier: Topic :: Software Development :: Libraries
Classifier: Topic :: System :: Filesystems
Classifier: Topic :: System :: Monitoring
Classifier: Topic :: Utilities
Requires: ansicolors
Requires: click
Requires: watchdog
Requires-Python: >=3.6
Requires-Dist: ansicolors (>=1.1.8)
Requires-Dist: click (>=7.1.2)
Requires-Dist: watchdog (>=1.0.2)
